pyformex_arraytools/__init__.py
pyformex_arraytools/arraytools.py
pyformex_arraytools/varray.py
pyformex_arraytools-3.3.1.dist-info/LICENSE
pyformex_arraytools-3.3.1.dist-info/METADATA
pyformex_arraytools-3.3.1.dist-info/WHEEL
pyformex_arraytools-3.3.1.dist-info/top_level.txt
pyformex_arraytools-3.3.1.dist-info/RECORD
