Metadata-Version: 2.1
Name: pyformex-arraytools
Version: 3.3.1
Summary: Array tools from the pyFormex project
Author-email: Benedict Verhegghe <bverheg@gmail.com>
Project-URL: Homepage, https://pyformex.org
Project-URL: Bug Tracker, https://gitlab.com/bverheg/pyformex/-/issues
Classifier: Programming Language :: Python :: 3
Classifier: License :: OSI Approved :: GNU General Public License v3 or later (GPLv3+)
Classifier: Operating System :: POSIX :: Linux
Classifier: Operating System :: POSIX
Classifier: Development Status :: 5 - Production/Stable
Requires-Python: >=3.8
License-File: LICENSE
